Metadata-Version: 2.4
Name: textminer-pro-asddzxqw-test
Version: 0.1.1
Summary: 텍스트 분석을 위한 Python 패키지
Home-page: https://github.com/asddzxqw/textminer-pro
Author: asddzxqw
Author-email: kk020929@naver.com
Classifier: Development Status :: 3 - Alpha
Classifier: Intended Audience :: Developers
Classifier: License :: OSI Approved :: MIT License
Classifier: Operating System :: OS Independent
Classifier: Programming Language :: Python :: 3
Classifier: Programming Language :: Python :: 3.7
Classifier: Programming Language :: Python :: 3.8
Classifier: Programming Language :: Python :: 3.9
Classifier: Programming Language :: Python :: 3.10
Requires-Python: >=3.7
License-File: LICENSE
Requires-Dist: nltk
Requires-Dist: scikit-learn
Requires-Dist: numpy
Requires-Dist: langdetect
Dynamic: author
Dynamic: author-email
Dynamic: classifier
Dynamic: description
Dynamic: description-content-type
Dynamic: home-page
Dynamic: license-file
Dynamic: requires-dist
Dynamic: requires-python
Dynamic: summary
